{
    "skin": {
        "blood_volume_fraction": 0.056446486410056555,
        "ScvO2": 0.6045625439207081,
        "water_volume": 0.911347857686164,
        "fat_volume": 0.1116538886440726,
        "melanin_volume": 0.03283555958187255,
        "collagen_volume": 0,
        "n": 1.4,
        "g": 0.71,
        "muspx": 32.8758839265081,
        "bmie": 1.6638937933017348
    },
    "fat": {
        "blood_volume_fraction": 0.004853790103110982,
        "ScvO2": 0.5535033541424075,
        "water_volume": 0,
        "fat_volume": 0.9514292244382134,
        "melanin_volume": 0,
        "collagen_volume": 0,
        "n": 1.4,
        "g": 0.9,
        "muspx": 22.446193148045353,
        "bmie": 0.7942219566575541
    },
    "muscle": {
        "blood_volume_fraction": 0.08604918901615799,
        "ScvO2": 0.22358667957223988,
        "water_volume": 0.3414903581685533,
        "fat_volume": 0,
        "melanin_volume": 0,
        "collagen_volume": 0.5601373821899738,
        "n": 1.4,
        "g": 0.9,
        "muspx": 12.391136022858511,
        "bmie": 0.980686027152415
    },
    "IJV": {
        "blood_volume_fraction": 1.0,
        "ScvO2": 0.5934751780986627,
        "water_volume": 0,
        "fat_volume": 0,
        "melanin_volume": 0,
        "collagen_volume": 0,
        "n": 1.4,
        "g": 0.9,
        "muspx": 0.5606912780256991,
        "bmie": 1.0
    },
    "CCA": {
        "blood_volume_fraction": 1.0,
        "ScvO2": 0.9781751402375247,
        "water_volume": 0,
        "fat_volume": 0,
        "melanin_volume": 0,
        "collagen_volume": 0,
        "n": 1.4,
        "g": 0.94,
        "muspx": 0.52869628823254,
        "bmie": 1.0
    },
    "geometry": [
        1.27,
        1.0,
        7.71,
        14.95,
        3.53,
        23.86,
        7.68
    ],
    "spec_rmsp": 5.08173129206307,
    "absorb_rmsp": 91.22561236838276
}