{
    "skin": {
        "n": 1.4,
        "g": 0.94,
        "muspx": 36.638779014024934,
        "bmie": 0.959039276581137
    },
    "fat": {
        "n": 1.4,
        "g": 0.94,
        "muspx": 23.711900522265008,
        "bmie": 0.804861549549426
    },
    "muscle": {
        "n": 1.4,
        "g": 0.94,
        "muspx": 10.63265511350986,
        "bmie": 2.480750619560387
    },
    "IJV": {
        "n": 1.4,
        "g": 0.94,
        "muspx": 18.956607679854454,
        "bmie": 1.0
    },
    "CCA": {
        "n": 1.4,
        "g": 0.94,
        "muspx": 13.26904135049859,
        "bmie": 1.0
    },
    "geometry": {
        "skin_thickness": 0.8621455511877347,
        "fat_thickness": 1.0834058863900704,
        "ijv_radius": 4.874653667689032,
        "ijv_depth": 9.212229974008503,
        "cca_radius": 2.7656822477646443,
        "cca_depth": 20.717103506740834,
        "ijv_cca_distance": 5.971158627221373
    },
    "boundary": {
        "x_size": 150,
        "y_size": 150,
        "z_size": 200
    },
    "idx": "bw5hnaTD37"
}