{
    "skin": {
        "n": 1.4,
        "g": 0.94,
        "muspx": 44.30170160440756,
        "bmie": 0.8074582607701938
    },
    "fat": {
        "n": 1.4,
        "g": 0.94,
        "muspx": 14.358698461731802,
        "bmie": 0.7017079237928415
    },
    "muscle": {
        "n": 1.4,
        "g": 0.94,
        "muspx": 10.844127757604669,
        "bmie": 2.021404035254635
    },
    "IJV": {
        "n": 1.4,
        "g": 0.94,
        "muspx": 14.06289165481516,
        "bmie": 1.0
    },
    "CCA": {
        "n": 1.4,
        "g": 0.94,
        "muspx": 15.859967786499917,
        "bmie": 1.0
    },
    "geometry": {
        "skin_thickness": 0.9175223217137177,
        "fat_thickness": 1.0912720058996883,
        "ijv_radius": 7.468981097090388,
        "ijv_depth": 6.3841982044117955,
        "cca_radius": 3.576311465458328,
        "cca_depth": 25.384926496190452,
        "ijv_cca_distance": 5.460317488033816
    },
    "boundary": {
        "x_size": 70,
        "y_size": 150,
        "z_size": 200
    },
    "idx": "CyHThSPY8o"
}