{
    "skin": {
        "n": 1.4,
        "g": 0.94,
        "muspx": 29.95105517312603,
        "bmie": 0.9206149406178153
    },
    "fat": {
        "n": 1.4,
        "g": 0.94,
        "muspx": 18.397626109179857,
        "bmie": 0.719202799710086
    },
    "muscle": {
        "n": 1.4,
        "g": 0.94,
        "muspx": 12.859967554875283,
        "bmie": 2.3964885814218073
    },
    "IJV": {
        "n": 1.4,
        "g": 0.94,
        "muspx": 16.979315181710803,
        "bmie": 1.0
    },
    "CCA": {
        "n": 1.4,
        "g": 0.94,
        "muspx": 19.94004229640397,
        "bmie": 1.0
    },
    "geometry": {
        "skin_thickness": 1.2736179653782471,
        "fat_thickness": 0.6144967948662943,
        "ijv_radius": 3.1882450118162096,
        "ijv_depth": 8.07775952029765,
        "cca_radius": 3.791728192317266,
        "cca_depth": 20.40901723518168,
        "ijv_cca_distance": 8.217131178905928
    },
    "boundary": {
        "x_size": 150,
        "y_size": 150,
        "z_size": 200
    },
    "idx": "IRWQIF85Lm"
}