{
    "skin": {
        "n": 1.4,
        "g": 0.94,
        "muspx": 30.21532244364513,
        "bmie": 1.2466366986613822
    },
    "fat": {
        "n": 1.4,
        "g": 0.94,
        "muspx": 31.361133051688867,
        "bmie": 0.9405906019742103
    },
    "muscle": {
        "n": 1.4,
        "g": 0.94,
        "muspx": 10.335085521363427,
        "bmie": 1.1124498799448534
    },
    "IJV": {
        "n": 1.4,
        "g": 0.94,
        "muspx": 10.050596198640491,
        "bmie": 1.0
    },
    "CCA": {
        "n": 1.4,
        "g": 0.94,
        "muspx": 12.205374578387733,
        "bmie": 1.0
    },
    "geometry": {
        "skin_thickness": 1.4951311968186674,
        "fat_thickness": 1.296231213649469,
        "ijv_radius": 5.487280543734613,
        "ijv_depth": 13.71708946620393,
        "cca_radius": 3.317170807014155,
        "cca_depth": 25.569169490024652,
        "ijv_cca_distance": 5.655339803793708
    },
    "boundary": {
        "x_size": 150,
        "y_size": 150,
        "z_size": 200
    },
    "idx": "j7ysv5Gl4I"
}