{
    "skin": {
        "n": 1.4,
        "g": 0.94,
        "muspx": 47.595408644084216,
        "bmie": 1.9669111191827957
    },
    "fat": {
        "n": 1.4,
        "g": 0.94,
        "muspx": 21.31092703388777,
        "bmie": 0.4666090672454432
    },
    "muscle": {
        "n": 1.4,
        "g": 0.94,
        "muspx": 11.337185395636771,
        "bmie": 1.6231575108899057
    },
    "IJV": {
        "n": 1.4,
        "g": 0.94,
        "muspx": 19.614986553609697,
        "bmie": 1.0
    },
    "CCA": {
        "n": 1.4,
        "g": 0.94,
        "muspx": 10.08753157665216,
        "bmie": 1.0
    },
    "geometry": {
        "skin_thickness": 0.9045609111674425,
        "fat_thickness": 0.7360155637889007,
        "ijv_radius": 4.222155876184365,
        "ijv_depth": 7.7786247409690805,
        "cca_radius": 4.199685961916809,
        "cca_depth": 20.728273653607136,
        "ijv_cca_distance": 5.327177218677558
    },
    "boundary": {
        "x_size": 70,
        "y_size": 150,
        "z_size": 200
    },
    "idx": "yOrWcACzH7"
}